conetwork_test-0.1.15.dist-info/METADATA
conetwork_test-0.1.15.dist-info/WHEEL
fleece_network/peer.py
fleece_network/__init__.py
fleece_network/py.typed
fleece_network/serde.py
fleece_network/fleece_network_rust.cpython-311-x86_64-linux-gnu.so
conetwork_test-0.1.15.dist-info/RECORD
